friendlycrypto.py
friendlycrypto-1.0.0.dist-info/METADATA
friendlycrypto-1.0.0.dist-info/WHEEL
friendlycrypto-1.0.0.dist-info/top_level.txt
friendlycrypto-1.0.0.dist-info/RECORD
