Metadata-Version: 2.1
Name: friendlycrypto
Version: 1.0.0
Summary: Encrypt and decrypt Python objects with just one line of code! 🔥🔐🕵️
Home-page: https://github.com/RealA10N/friendlycrypto
Author: Alon Krymgand Osovsky
Author-email: downtown2u@gmail.com
License: UNKNOWN
Platform: UNKNOWN
Classifier: Programming Language :: Python :: 3 :: Only
Classifier: Programming Language :: Python :: 3.6
Classifier: Programming Language :: Python :: 3.7
Classifier: Programming Language :: Python :: 3.8
Classifier: Programming Language :: Python :: 3.9
Classifier: Programming Language :: Python :: 3.10
Classifier: Development Status :: 4 - Beta
Classifier: Topic :: Security
Classifier: Topic :: Security :: Cryptography
Classifier: Topic :: Database
Requires-Python: >=3.6
Requires-Dist: cryptography (<4.0,>=3.4)
